mainzelliste_client/__init__.py
mainzelliste_client/client.py
mainzelliste_client-0.1.1.dist-info/licenses/LICENSE
mainzelliste_client-0.1.1.dist-info/METADATA
mainzelliste_client-0.1.1.dist-info/WHEEL
mainzelliste_client-0.1.1.dist-info/top_level.txt
mainzelliste_client-0.1.1.dist-info/RECORD
