Metadata-Version: 2.4
Name: mainzelliste-client
Version: 0.1.1
Summary: Client for Mainzelliste, a pseudonymization service.
Requires-Python: >=3.11
License-File: LICENSE
Requires-Dist: pytest>=9.0.2
Requires-Dist: requests>=2.32.5
Dynamic: license-file
